whisk/__init__.py
whisk/cd.py
whisk/dvc.py
whisk/git.py
whisk/log.py
whisk/model_stub.py
whisk/project.py
whisk/setup.py
whisk/whisk.py
whisk/cli/__init__.py
whisk/cli/cli.py
whisk/cli/log_tree.py
whisk/cli/whisk_multi_command.py
whisk/cli/commands/__init__.py
whisk/cli/commands/create.py
whisk/cli/commands/project/__init__.py
whisk/cli/commands/project/app.py
whisk/cli/commands/project/dvc.py
whisk/cli/commands/project/notebook.py
whisk/cli/commands/project/package.py
whisk/cli/commands/project/s3.py
whisk/cli/commands/project/setup.py
whisk/template/LICENSE
whisk/template/cookiecutter.json
whisk/template/{{ cookiecutter.repo_name }}/.envrc.example
whisk/template/{{ cookiecutter.repo_name }}/.gitignore
whisk/template/{{ cookiecutter.repo_name }}/.slugignore
whisk/template/{{ cookiecutter.repo_name }}/MANIFEST.in
whisk/template/{{ cookiecutter.repo_name }}/README.md
whisk/template/{{ cookiecutter.repo_name }}/requirements.txt
whisk/template/{{ cookiecutter.repo_name }}/setup.py
whisk/template/{{ cookiecutter.repo_name }}/tox.ini
whisk/template/{{ cookiecutter.repo_name }}/.whisk/config.yml
whisk/template/{{ cookiecutter.repo_name }}/app/Procfile
whisk/template/{{ cookiecutter.repo_name }}/app/Procfile.dev
whisk/template/{{ cookiecutter.repo_name }}/app/README.md
whisk/template/{{ cookiecutter.repo_name }}/app/main.py
whisk/template/{{ cookiecutter.repo_name }}/app/test_app.py
whisk/template/{{ cookiecutter.repo_name }}/data/external/.gitkeep
whisk/template/{{ cookiecutter.repo_name }}/data/interim/.gitkeep
whisk/template/{{ cookiecutter.repo_name }}/data/processed/.gitkeep
whisk/template/{{ cookiecutter.repo_name }}/data/raw/.gitkeep
whisk/template/{{ cookiecutter.repo_name }}/docs/Makefile
whisk/template/{{ cookiecutter.repo_name }}/docs/commands.rst
whisk/template/{{ cookiecutter.repo_name }}/docs/conf.py
whisk/template/{{ cookiecutter.repo_name }}/docs/getting-started.rst
whisk/template/{{ cookiecutter.repo_name }}/docs/index.rst
whisk-0.1.32.dist-info/LICENSE
whisk-0.1.32.dist-info/METADATA
whisk-0.1.32.dist-info/WHEEL
whisk-0.1.32.dist-info/entry_points.txt
whisk-0.1.32.dist-info/top_level.txt
whisk-0.1.32.dist-info/RECORD
