Metadata-Version: 2.1
Name: whisk
Version: 0.1.32
Summary: Machine Learning Project Framework Generator
Home-page: https://github.com/bookletai/whisk
Author: Derek Haynes
Author-email: derek@dlite.cc
License: MIT license
Keywords: whisk
Platform: UNKNOWN
Classifier: Development Status :: 2 - Pre-Alpha
Classifier: Intended Audience :: Developers
Classifier: License :: OSI Approved :: MIT License
Classifier: Natural Language :: English
Classifier: Programming Language :: Python :: 3
Classifier: Programming Language :: Python :: 3.6
Classifier: Programming Language :: Python :: 3.7
Classifier: Programming Language :: Python :: 3.8
Requires-Python: >=3.6
Requires-Dist: Click (>=7.0)
Requires-Dist: cookiecutter (>=1.7.2)
